build/lib/clickhouse_easy_connect_ivi/__init__.py
build/lib/clickhouse_easy_connect_ivi/clickhouse_client.py
clickhouse_easy_connect_ivi/__init__.py
clickhouse_easy_connect_ivi/clickhouse_client.py
clickhouse_easy_connect_ivi-1.2.0.dist-info/licenses/LICENSE
clickhouse_easy_connect_ivi-1.2.0.dist-info/METADATA
clickhouse_easy_connect_ivi-1.2.0.dist-info/WHEEL
clickhouse_easy_connect_ivi-1.2.0.dist-info/top_level.txt
clickhouse_easy_connect_ivi-1.2.0.dist-info/RECORD
