Metadata-Version: 2.4
Name: clickhouse-easy-connect-ivi
Version: 1.2.0
Summary: Упрощенная библиотека для работы с ClickHouse
Home-page: https://github.com/your-company/clickhouse-easy-connect-ivi
Author: Your Name
Author-email: D Garin <dgarin@example.com>
License-Expression: MIT
Project-URL: Homepage, https://github.com/your-company/clickhouse-easy-connect-ivi
Project-URL: Repository, https://github.com/your-company/clickhouse-easy-connect-ivi.git
Project-URL: Issues, https://github.com/your-company/clickhouse-easy-connect-ivi/issues
Classifier: Development Status :: 4 - Beta
Classifier: Intended Audience :: Developers
Classifier: Operating System :: OS Independent
Classifier: Programming Language :: Python :: 3
Classifier: Programming Language :: Python :: 3.7
Classifier: Programming Language :: Python :: 3.8
Classifier: Programming Language :: Python :: 3.9
Classifier: Programming Language :: Python :: 3.10
Classifier: Programming Language :: Python :: 3.11
Classifier: Programming Language :: Python :: 3.12
Requires-Python: >=3.7
License-File: LICENSE
Requires-Dist: pandas>=1.0.0
Requires-Dist: clickhouse-connect>=0.5.0
Requires-Dist: PyYAML>=5.0.0
Provides-Extra: dev
Requires-Dist: pytest>=6.0; extra == "dev"
Requires-Dist: pytest-cov; extra == "dev"
Requires-Dist: black; extra == "dev"
Requires-Dist: isort; extra == "dev"
Requires-Dist: flake8; extra == "dev"
Dynamic: author
Dynamic: home-page
Dynamic: license-file
Dynamic: requires-python
